<?xml version="1.0" encoding="utf-8" standalone="yes"?>
<window>
<controls>

		<control>
			<description>BG</description>
			<type>image</type>
			<id>1</id>
            <posX>0</posX>
            <posY>0</posY>
            <width>1366</width>
            <height>768</height>
            <texture>background.png</texture>
		</control>

		<control>
			<description>Fanart Background</description>
			<type>image</type>
			<id>1</id>
			<posX>0</posX>
			<posY>0</posY>
			<width>1366</width>
			<height>768</height>
			<texture>#header.background</texture>	
			<visible>string.contains(#maya.backgroundImage,yes)</visible>
		</control>

		<control>
			<description>Fanart Overlay</description>
			<type>image</type>
			<id>1</id>
			<posX>0</posX>
			<posY>0</posY>
			<width>1366</width>
			<height>768</height>
			<texture>basichome_fanart_overlay.png</texture>
			<visible>string.contains(#maya.backgroundImage,yes)</visible>
		</control>
		
	<control>
		<type>label</type>
		<id>1</id>
		<posX>552</posX>
		<posY>30</posY>
		<width>500</width>
		<height>100</height>
		<label>#header.label</label>
		<textcolor>6aa5cb</textcolor>
		<font>Segoe Light40</font>
		<animation effect="fade" time="100">WindowOpen</animation>
		<animation effect="fade" time="100">WindowClose</animation>
	</control>
	
	<control>
		<type>label</type>
		<id>1</id>
		<posX>552</posX>
		<posY>120</posY>
		<width>500</width>
		<height>100</height>
		<label>5</label>
		<font>Segoe Light22</font>
		<animation effect="fade" time="100">WindowOpen</animation>
		<animation effect="fade" time="100">WindowClose</animation>
	</control>

</controls>
</window>
