<window>
<id>6622</id>
<defaultcontrol>110</defaultcontrol>
<allowoverlay>no</allowoverlay>
<controls>
	<control>
		<description>BackGround</description>
		<type>image</type>
		<id>6</id>
		<posX>0</posX>
		<posY>0</posY>
		<width>1366</width>
		<height>768</height>
		<texture>background.png</texture>
	</control>

	<control>
		<description>header</description>
		<type>image</type>
		<id>30</id>
		<posX>75</posX>
		<posY>45</posY>
		<texture flipY="true" diffuse="Thumb_Mask.png">musictrivia.png</texture>
	</control>

	<control>
		<description>Start Button</description>
		<type>button</type>
		<id>110</id>
		<posX>60</posX>
		<posY>97</posY>
		<label>Start</label>
		<onleft>110</onleft>
		<onright>9</onright>
		<onup>1</onup>
		<ondown>2</ondown>
	</control>

	<control>
		<description>Stop</description>
		<type>button</type>
		<id>2</id>
		<posX>60</posX>
		<posY>135</posY>
		<label>Stop</label>
		<onleft>2</onleft>
		<onright>9</onright>
		<onup>110</onup>
		<ondown>4</ondown>
	</control>

	<control>
		<description>time</description>
		<type>button</type>
		<id>3</id>
		<posX>60</posX>
		<posY>212</posY>
		<label>Time: 15</label>
		<onleft>3</onleft>
		<onright>9</onright>
		<onup>4</onup>
		<ondown>3</ondown>
	</control>

	<control>
		<description>tries</description>
		<type>button</type>
		<id>4</id>
		<posX>60</posX>
		<posY>173</posY>
		<label>Tries: 2</label>
		<onleft>4</onleft>
		<onright>9</onright>
		<onup>2</onup>
		<ondown>3</ondown>
	</control>

	<control>
		<type>label</type>
		<id>10</id>
		<posX>380</posX>
		<posY>245</posY>
		<label>:00</label>
		<font>font72</font>
		<align>left</align>
		<textcolor>White</textcolor>
		<animation effect="fade" time="200">WindowOpen</animation>
		<animation effect="fade" time="200">WindowClose</animation>
	</control>

	<control>
		<type>label</type>
		<id>11</id>
		<posX>445</posX>
		<posY>425</posY>
		<label>Points</label>
		<font>font18</font>
		<align>left</align>
		<textcolor>White</textcolor>
		<animation effect="fade" time="200">WindowOpen</animation>
		<animation effect="fade" time="200">WindowClose</animation>
	</control>

	<control>
		<type>label</type>
		<id>12</id>
		<posX>395</posX>
		<posY>415</posY>
		<label></label>
		<font>font32</font>
		<align>left</align>
		<textcolor>White</textcolor>
		<animation effect="fade" time="200">WindowOpen</animation>
		<animation effect="fade" time="200">WindowClose</animation>
	</control>

	<control>
		<type>label</type>
		<description>Player 1 label</description>
		<id>100</id>
		<posX>75</posX>
		<posY>265</posY>
		<label>Player 1</label>
		<font>font18</font>
		<align>left</align>
		<visible>false</visible>
		<textcolor>White</textcolor>
		<animation effect="fade" time="200">WindowOpen</animation>
		<animation effect="fade" time="200">WindowClose</animation>
	</control>

	<control>
		<type>label</type>
		<description>p1 correct: label</description>
		<id>13</id>
		<posX>75</posX>
		<posY>325</posY>
		<label>Correct:</label>
		<font>font12</font>
		<align>left</align>
		<textcolor>White</textcolor>
		<animation effect="fade" time="200">WindowOpen</animation>
		<animation effect="fade" time="200">WindowClose</animation>
	</control>

	<control>
		<type>label</type>
		<id>14</id>
		<description>p1 number of correct label</description>
		<posX>155</posX>
		<posY>325</posY>
		<label></label>
		<font>font12</font>
		<align>left</align>
		<textcolor>White</textcolor>
		<animation effect="fade" time="200">WindowOpen</animation>
		<animation effect="fade" time="200">WindowClose</animation>
	</control>

	<control>
		<type>label</type>
		<id>15</id>
		<description>p1 wrong: label</description>
		<posX>75</posX>
		<posY>365</posY>
		<label>Wrong:</label>
		<font>font12</font>
		<align>left</align>
		<textcolor>White</textcolor>
		<animation effect="fade" time="200">WindowOpen</animation>
		<animation effect="fade" time="200">WindowClose</animation>
	</control>

	<control>
		<type>label</type>
		<id>16</id>
		<description>p1 number wrong label</description>
		<posX>155</posX>
		<posY>365</posY>
		<label></label>
		<font>font12</font>
		<align>left</align>
		<textcolor>White</textcolor>
		<animation effect="fade" time="200">WindowOpen</animation>
		<animation effect="fade" time="200">WindowClose</animation>
	</control>

	<control>
		<type>label</type>
		<id>17</id>
		<description>p1 score: label</description>
		<posX>75</posX>
		<posY>405</posY>
		<label>Score:</label>
		<font>font18</font>
		<align>left</align>
		<textcolor>White</textcolor>
		<animation effect="fade" time="200">WindowOpen</animation>
		<animation effect="fade" time="200">WindowClose</animation>
	</control>

	<control>
		<type>label</type>
		<id>18</id>
		<description>p1 number score label</description>
		<posX>200</posX>
		<posY>408</posY>
		<label></label>
		<font>font18</font>
		<align>left</align>
		<textcolor>White</textcolor>
		<animation effect="fade" time="200">WindowOpen</animation>
		<animation effect="fade" time="200">WindowClose</animation>
	</control>

	<control>
		<type>label</type>
		<description>Player 2 label</description>
		<id>20</id>
		<posX>75</posX>
		<posY>495</posY>
		<label>Player 2</label>
		<font>font18</font>
		<align>left</align>
		<visible>false</visible>
		<textcolor>White</textcolor>
		<animation effect="fade" time="200">WindowOpen</animation>
		<animation effect="fade" time="200">WindowClose</animation>
	</control>

	<control>
		<type>label</type>
		<description>p2 correct: label</description>
		<id>23</id>
		<posX>75</posX>
		<posY>555</posY>
		<label>Correct:</label>
		<font>font12</font>
		<align>left</align>
		<visible>false</visible>
		<textcolor>White</textcolor>
		<animation effect="fade" time="200">WindowOpen</animation>
		<animation effect="fade" time="200">WindowClose</animation>
	</control>

	<control>
		<type>label</type>
		<id>24</id>
		<description>p2 number of correct label</description>
		<posX>155</posX>
		<posY>555</posY>
		<label></label>
		<font>font12</font>
		<align>left</align>
		<visible>false</visible>
		<textcolor>White</textcolor>
		<animation effect="fade" time="200">WindowOpen</animation>
		<animation effect="fade" time="200">WindowClose</animation>
	</control>

	<control>
		<type>label</type>
		<id>25</id>
		<description>p2 wrong: label</description>
		<posX>75</posX>
		<posY>595</posY>
		<label>Wrong:</label>
		<font>font12</font>
		<align>left</align>
		<visible>false</visible>
		<textcolor>White</textcolor>
		<animation effect="fade" time="200">WindowOpen</animation>
		<animation effect="fade" time="200">WindowClose</animation>
	</control>

	<control>
		<type>label</type>
		<id>26</id>
		<description>p2 number wrong label</description>
		<posX>155</posX>
		<posY>595</posY>
		<label></label>
		<font>font12</font>
		<align>left</align>
		<visible>false</visible>
		<textcolor>White</textcolor>
		<animation effect="fade" time="200">WindowOpen</animation>
		<animation effect="fade" time="200">WindowClose</animation>
	</control>

	<control>
		<type>label</type>
		<id>27</id>
		<description>p2 score: label</description>
		<posX>75</posX>
		<posY>635</posY>
		<label>Score:</label>
		<font>font18</font>
		<align>left</align>
		<visible>false</visible>
		<textcolor>White</textcolor>
		<animation effect="fade" time="200">WindowOpen</animation>
		<animation effect="fade" time="200">WindowClose</animation>
	</control>

	<control>
		<type>label</type>
		<id>28</id>
		<description>p2 number score label</description>
		<posX>200</posX>
		<posY>638</posY>
		<label></label>
		<font>font18</font>
		<align>left</align>
		<visible>false</visible>
		<textcolor>White</textcolor>
		<animation effect="fade" time="200">WindowOpen</animation>
		<animation effect="fade" time="200">WindowClose</animation>
	</control>

	<control>
		<type>listcontrol</type>
		<description>answers</description>
		<id>9</id>
		<posX>600</posX>
		<posY>20</posY>
		<height>600</height>
		<width>750</width>
		<onleft>2</onleft>
		<onright>9</onright>
		<onup>9</onup>
		<ondown>9</ondown>
		<font>font16</font>
		<font2>font12</font2>
		<font3>font12</font3>
		<textXOff>27</textXOff>
		<textXOff2>780</textXOff2>
		<textXOff3>172</textXOff3>
		<textYOff>12</textYOff>
		<textYOff2>88</textYOff2>
		<textYOff3>48</textYOff3>
		<IconXOff>22</IconXOff>
		<IconYOff>16</IconYOff>
		<textcolor2>ffa9d0f7</textcolor2>
		<textcolor3>ffa9d0f7</textcolor3>
		<itemHeight>100</itemHeight>
		<itemWidth>133</itemWidth>
		<textureHeight>133</textureHeight>
		<keepaspectratio>yes</keepaspectratio>
	</control>

</controls>
</window>
