<?xml version="1.0" encoding="utf-8" standalone="yes"?>
<window>
  <id>700</id>
  <defaultcontrol>24</defaultcontrol>
  <allowoverlay>yes</allowoverlay>
  <define>#header.background:hover_settings.png</define>
  <controls>
  
    <import>common.window.background.xml</import>
    <import>settings.menu.xml</import>
	
    <control>
      <type>image</type>
      <id>1</id>
      <posX>610</posX>
      <posY>84</posY>
      <width>1152</width>
      <height>900</height>
      <texture>settings_main_panel.png</texture>
    </control>
	
    <control>
      <animation effect="fade" time="100">WindowOpen</animation>
      <animation effect="fade" time="100">WindowClose</animation>
      <type>label</type>
      <id>1</id>
      <posX>708</posX>
      <posY>175</posY>
      <width>702</width>
      <height>140</height>
      <label>605</label>
      <textcolor>6aa5cb</textcolor>
      <font>Segoe Light40</font>
      <valign>middle</valign>
    </control>
	
    <control>
      <description>buttons</description>
      <type>group</type>
      <animation effect="fade" time="250">WindowOpen</animation>
      <animation effect="fade" time="250">WindowClose</animation>
      <posX>688</posX>
      <posY>365</posY>
      <layout>GridLayout(2, 7, 42, 0, 1)</layout>
      <control>
	  
        <description>MPEG-2 Video Codecs</description>
        <type>button</type>
        <width>469</width>
        <textureFocus>settings_button_medium_focus.png</textureFocus>
        <textureNoFocus>-</textureNoFocus>
        <textcolor>ff85cffe</textcolor>
        <textcolorNoFocus>ff85cffe</textcolorNoFocus>
        <id>24</id>
        <label>6000</label>
        <onup>32</onup>
        <ondown>35</ondown>				
      </control>
	  
      <control>
        <description>H.264 Video Codecs</description>
        <type>button</type>
        <width>469</width>
        <textureFocus>settings_button_medium_focus.png</textureFocus>
        <textureNoFocus>-</textureNoFocus>
        <textcolor>ff85cffe</textcolor>
        <textcolorNoFocus>ff85cffe</textcolorNoFocus>
        <id>35</id>
        <label>6036</label>
        <onup>24</onup>
        <ondown>25</ondown>			
      </control>
	  
      <control>
        <description>Audio Codecs</description>
        <type>button</type>
        <width>469</width>
        <textureFocus>settings_button_medium_focus.png</textureFocus>
        <textureNoFocus>-</textureNoFocus>
        <textcolor>ff85cffe</textcolor>
        <textcolorNoFocus>ff85cffe</textcolorNoFocus>
        <id>25</id>
        <label>6001</label>
        <onup>35</onup>		
        <ondown>36</ondown>			
      </control>
	  
      <control>
        <description>LATM AAC Audio Codecs</description>
        <type>button</type>
        <width>469</width>
        <textureFocus>settings_button_medium_focus.png</textureFocus>
        <textureNoFocus>-</textureNoFocus>
        <textcolor>ff85cffe</textcolor>
        <textcolorNoFocus>ff85cffe</textcolorNoFocus>
        <id>36</id>
        <label>6039</label>
      </control>
	  
      <control>
        <description>Audio Renderer</description>
        <type>button</type>
        <width>469</width>
        <textureFocus>settings_button_medium_focus.png</textureFocus>
        <textureNoFocus>-</textureNoFocus>
        <textcolor>ff85cffe</textcolor>
        <textcolorNoFocus>ff85cffe</textcolorNoFocus>
        <id>33</id>
        <label>6002</label>
      </control>
	  
      <control>
        <description>De-interlacing</description>
        <type>button</type>
        <width>469</width>
        <textureFocus>settings_button_medium_focus.png</textureFocus>
        <textureNoFocus>-</textureNoFocus>
        <textcolor>ff85cffe</textcolor>
        <textcolorNoFocus>ff85cffe</textcolorNoFocus>
        <id>27</id>
        <label>6003</label>
      </control>
	  
      <control>
        <description>Aspect Ratio</description>
        <type>button</type>
        <width>469</width>
        <textureFocus>settings_button_medium_focus.png</textureFocus>
        <textureNoFocus>-</textureNoFocus>
        <textcolor>ff85cffe</textcolor>
        <textcolorNoFocus>ff85cffe</textcolorNoFocus>
        <id>28</id>
        <label>6004</label>
        <ondown>30</ondown>
      </control>
	  
      <control>
        <description>Automatically turn TV on</description>
        <type>button</type>
        <width>469</width>
        <textureFocus>settings_button_medium_focus.png</textureFocus>
        <textureNoFocus>-</textureNoFocus>
        <textcolor>ff85cffe</textcolor>
        <textcolorNoFocus>ff85cffe</textcolorNoFocus>
        <id>30</id>
        <label>6006</label>
        <onup>28</onup>		
        <ondown>34</ondown>		
      </control>
	  
      <control>
        <description>ChannelManager</description>
        <type>button</type>
        <id>34</id>
        <label>#TV.Settings.ChannelManagerName</label>
		<hyperlink>49856</hyperlink>
        <width>469</width>	
        <ondown>31</ondown>		
        <textureFocus>settings_button_medium_focus.png</textureFocus>
        <textureNoFocus>-</textureNoFocus>
        <textcolor>ff85cffe</textcolor>
        <textcolorNoFocus>ff85cffe</textcolorNoFocus>		
		<visible>plugin.isenabled(For The Record TV)</visible>
      </control>
	  
      <control>
        <description>4TRClientSettings</description>
        <type>button</type>
        <id>31</id>
        <label>#TV.Settings.4TRClientSettingsName</label>
		<hyperlink>49857</hyperlink>
        <width>469</width>		
        <ondown>32</ondown>		
        <textureFocus>settings_button_medium_focus.png</textureFocus>
        <textureNoFocus>-</textureNoFocus>
        <textcolor>ff85cffe</textcolor>
        <textcolorNoFocus>ff85cffe</textcolorNoFocus>		
		<visible>plugin.isenabled(For The Record TV)</visible>
      </control>
	  
      <control>
        <description>4TRServerSettings</description>
        <type>button</type>
        <id>32</id>
        <label>#TV.Settings.4TRServerSettingsName</label>
		<hyperlink>49855</hyperlink>
        <width>469</width>
        <ondown>24</ondown>		
        <textureFocus>settings_button_medium_focus.png</textureFocus>
        <textureNoFocus>-</textureNoFocus>
        <textcolor>ff85cffe</textcolor>
        <textcolorNoFocus>ff85cffe</textcolorNoFocus>		
		<visible>plugin.isenabled(For The Record TV)</visible>
      </control>
	  
    </control>
	
  </controls>
</window>