<?xml version="1.0" encoding="utf-8" standalone="yes"?>
<window>
  <controls>
  
		<!-- Media logos [List View] -->
		<control>
			<description>Video Codec</description>
			<type>image</type>
			<id>0</id>
			<posX>765</posX>
			<posY>965</posY>
			<width>95</width>
			<height>45</height>
			<texture>Logos\video\#MovingPictures.LocalMedia.videocodec.png</texture>
			<visible>control.isvisible(50)+facadeview.list</visible>
		</control>

		<control>
			<description>Video Resolution</description>
			<type>image</type>
			<id>0</id>
			<posX>865</posX>
			<posY>965</posY>
			<width>95</width>
			<height>45</height>
			<texture>Logos\resolution\#MovingPictures.LocalMedia.videoresolution.png</texture>
			<visible>control.isvisible(50)+facadeview.list</visible>
		</control>

		<control>
			<description>Video Aspect Ratio</description>
			<type>image</type>
			<id>0</id>
			<posX>965</posX>
			<posY>965</posY>
			<width>95</width>
			<height>45</height>
			<texture>Logos\aspectratio\#MovingPictures.LocalMedia.videoaspectratio.png</texture>
			<visible>control.isvisible(50)+facadeview.list</visible>
		</control>

		<control>
			<description>Audio Codec</description>
			<type>image</type>
			<id>0</id>
			<posX>1065</posX>
			<posY>965</posY>
			<width>95</width>
			<height>45</height>
			<texture>Logos\audio\#MovingPictures.LocalMedia.audiocodec.png</texture>
			<visible>control.isvisible(50)+facadeview.list</visible>
		</control>

		<control>
			<description>Audio Channels</description>
			<type>image</type>
			<id>0</id>
			<posX>1165</posX>
			<posY>965</posY>
			<width>95</width>
			<height>45</height>
			<texture>Logos\audio\#MovingPictures.LocalMedia.audiochannels.png</texture>
			<visible>control.isvisible(50)+facadeview.list</visible>
		</control>

		<control>
			<description>Subtitles</description>
			<type>image</type>
			<id>0</id>
			<posX>1255</posX>
			<posY>965</posY>
			<width>95</width>
			<height>45</height>
			<texture>Logos\subtitles\#MovingPictures.LocalMedia.Subtitles.png</texture>
			<visible>control.isvisible(50)+facadeview.list</visible>
		</control>
	
  </controls>
</window>